{
  "hash": "b163b416",
  "configHash": "25636feb",
  "lockfileHash": "dd78f9c8",
  "browserHash": "28c73019",
  "optimized": {
    "vue": {
      "src": "../../../../node_modules/vue/dist/vue.runtime.esm-bundler.js",
      "file": "vue.js",
      "fileHash": "6f8ee698",
      "needsInterop": false
    },
    "vitepress > @vue/devtools-api": {
      "src": "../../../../node_modules/@vue/devtools-api/dist/index.js",
      "file": "vitepress___@vue_devtools-api.js",
      "fileHash": "11a83d18",
      "needsInterop": false
    },
    "vitepress > @vueuse/core": {
      "src": "../../../../node_modules/@vueuse/core/dist/index.js",
      "file": "vitepress___@vueuse_core.js",
      "fileHash": "893eced4",
      "needsInterop": false
    },
    "@iconify/vue": {
      "src": "../../../../node_modules/@iconify/vue/dist/iconify.mjs",
      "file": "@iconify_vue.js",
      "fileHash": "8cccc0c8",
      "needsInterop": false
    },
    "vitepress > @vueuse/integrations/useFocusTrap": {
      "src": "../../../../node_modules/@vueuse/integrations/dist/useFocusTrap.js",
      "file": "vitepress___@vueuse_integrations_useFocusTrap.js",
      "fileHash": "e7306eef",
      "needsInterop": false
    },
    "vitepress > mark.js/src/vanilla.js": {
      "src": "../../../../node_modules/mark.js/src/vanilla.js",
      "file": "vitepress___mark__js_src_vanilla__js.js",
      "fileHash": "af5bc0e6",
      "needsInterop": false
    },
    "vitepress > minisearch": {
      "src": "../../../../node_modules/minisearch/dist/es/index.js",
      "file": "vitepress___minisearch.js",
      "fileHash": "be56a12b",
      "needsInterop": false
    },
    "pinia": {
      "src": "../../../../node_modules/pinia/dist/pinia.mjs",
      "file": "pinia.js",
      "fileHash": "d316a4ac",
      "needsInterop": false
    },
    "vue-tippy": {
      "src": "../../../../node_modules/vue-tippy/dist/vue-tippy.esm-browser.js",
      "file": "vue-tippy.js",
      "fileHash": "4e5b5707",
      "needsInterop": false
    }
  },
  "chunks": {
    "chunk-LZ5A7EIH": {
      "file": "chunk-LZ5A7EIH.js"
    },
    "chunk-THFUG7Q6": {
      "file": "chunk-THFUG7Q6.js"
    },
    "chunk-VUQTIVY2": {
      "file": "chunk-VUQTIVY2.js"
    }
  }
}